configparser2dtypes/README.md
configparser2dtypes/__init__.py
configparser2dtypes/requirements.txt
configparser2dtypes/thirdparty.json
configparser2dtypes-0.10.dist-info/LICENSE.rst
configparser2dtypes-0.10.dist-info/METADATA
configparser2dtypes-0.10.dist-info/WHEEL
configparser2dtypes-0.10.dist-info/top_level.txt
configparser2dtypes-0.10.dist-info/RECORD
