Metadata-Version: 2.1
Name: configparser2dtypes
Version: 0.10
Summary: Loads configuration files, converts their values to appropriate data types, and obtains the processed data in different representations
Home-page: https://github.com/hansalemaos/configparser2dtypes
Author: Johannes Fischer
Author-email: aulasparticularesdealemaosp@gmail.com
License: MIT
Keywords: configparser,cfg,convert
Classifier: Development Status :: 4 - Beta
Classifier: Programming Language :: Python :: 3 :: Only
Classifier: Programming Language :: Python :: 3.10
Classifier: Topic :: Software Development :: Libraries :: Python Modules
Classifier: Topic :: Utilities
License-File: LICENSE.rst
Requires-Dist: deepcopyall
Requires-Dist: flatten-any-dict-iterable-or-whatsoever
Requires-Dist: isiter
Requires-Dist: tolerant-isinstance
